Workbook
Name Segment_Service: #N/A
Name Segment_Sexe: #N/A
Name Segment_Site: #N/A
Name Segment_Statut: #N/A

Sheet personel
A1: ID | B1: Nom | C1: Prénom | D1: Sexe | E1: Date de naissance | F1: Date d'entrée | G1: Site | H1: Service | I1: Statut | J1: Salaire brut mensuel | K1: Age | L1: Ancienneté | M1: Date Anniv. Contrat
A2: E0001 | B2: TEXIER | C2: Julie | D2: F | E2: 25393 | F2: 44402 | G2: Marseille | H2: Production | I2: CDD | J2: 3298.03 | K2: =DATEDIF(personel[[#This Row],[Date de naissance]], TODAY(), "Y") -> 56 | L2: =DATEDIF(personel[[#This Row],[Date d''entrée]], TODAY(), "Y") -> 4 | M2: =(EDATE(personel[[#This Row],[Date d''entrée]], 12)) -> 44767
A3: E0002 | B3: BODIN | C3: Camille | D3: H | E3: 32182 | F3: 42595 | G3: Marseille | H3: Commercial | I3: CDD | J3: 2917.04 | K3: =DATEDIF(personel[[#This Row],[Date de naissance]], TODAY(), "Y") -> 38 | L3: =DATEDIF(personel[[#This Row],[Date d''entrée]], TODAY(), "Y") -> 9 | M3: =(EDATE(personel[[#This Row],[Date d''entrée]], 12)) -> 42960
A4: E0003 | B4: MASSON | C4: Julien | D4: H | E4: 34404 | F4: 42540 | G4: Marseille | H4: Marketing | I4: CDI | J4: 3388.61 | K4: =DATEDIF(personel[[#This Row],[Date de naissance]], TODAY(), "Y") -> 32 | L4: =DATEDIF(personel[[#This Row],[Date d''entrée]], TODAY(), "Y") -> 9 | M4: =(EDATE(personel[[#This Row],[Date d''entrée]], 12)) -> 42905
A5: E0004 | B5: TECHER | C5: Agathe | D5: F | E5: 34766 | F5: 42477 | G5: Paris | H5: Marketing | I5: CDD | J5: 3913.82 | K5: =DATEDIF(personel[[#This Row],[Date de naissance]], TODAY(), "Y") -> 31 | L5: =DATEDIF(personel[[#This Row],[Date d''entrée]], TODAY(), "Y") -> 10 | M5: =(EDATE(personel[[#This Row],[Date d''entrée]], 12)) -> 42842
A6: E0005 | B6: MORVAN | C6: Maryse | D6: H | E6: 34597 | F6: 42413 | G6: Paris | H6: RH | I6: CDI | J6: 2859.51 | K6: =DATEDIF(personel[[#This Row],[Date de naissance]], TODAY(), "Y") -> 31 | L6: =DATEDIF(personel[[#This Row],[Date d''entrée]], TODAY(), "Y") -> 10 | M6: =(EDATE(personel[[#This Row],[Date d''entrée]], 12)) -> 42779
A7: E0006 | B7: GAUDIN | C7: Susanne | D7: H | E7: 29480 | F7: 44385 | G7: Marseille | H7: Informatique | I7: CDI | J7: 2859.52 | K7: =DATEDIF(personel[[#This Row],[Date de naissance]], TODAY(), "Y") -> 45 | L7: =DATEDIF(personel[[#This Row],[Date d''entrée]], TODAY(), "Y") -> 4 | M7: =(EDATE(personel[[#This Row],[Date d''entrée]], 12)) -> 44750
A8: E0007 | B8: THIERRY | C8: Paulette | D8: F | E8: 23567 | F8: 42333 | G8: Lyon | H8: Informatique | I8: CDI | J8: 3947.53 | K8: =DATEDIF(personel[[#This Row],[Date de naissance]], TODAY(), "Y") -> 61 | L8: =DATEDIF(personel[[#This Row],[Date d''entrée]], TODAY(), "Y") -> 10 | M8: =(EDATE(personel[[#This Row],[Date d''entrée]], 12)) -> 42699
A9: E0008 | B9: ROUSSEAU | C9: Madeleine | D9: F | E9: 36158 | F9: 42433 | G9: Paris | H9: Production | I9: CDI | J9: 3460.46 | K9: =DATEDIF(personel[[#This Row],[Date de naissance]], TODAY(), "Y") -> 27 | L9: =DATEDIF(personel[[#This Row],[Date d''entrée]], TODAY(), "Y") -> 10 | M9: =(EDATE(personel[[#This Row],[Date d''entrée]], 12)) -> 42798
A10: E0009 | B10: RAYNAUD | C10: Aurélie | D10: H | E10: 28442 | F10: 45352 | G10: Lyon | H10: Finance | I10: CDI | J10: 2718.32 | K10: =DATEDIF(personel[[#This Row],[Date de naissance]], TODAY(), "Y") -> 48 | L10: =DATEDIF(personel[[#This Row],[Date d''entrée]], TODAY(), "Y") -> 2 | M10: =(EDATE(personel[[#This Row],[Date d''entrée]], 12)) -> 45717
A11: E0010 | B11: GOSSELIN | C11: Clémence | D11: F | E11: 35975 | F11: 42357 | G11: Marseille | H11: Marketing | I11: CDI | J11: 3325.54 | K11: =DATEDIF(personel[[#This Row],[Date de naissance]], TODAY(), "Y") -> 27 | L11: =DATEDIF(personel[[#This Row],[Date d''entrée]], TODAY(), "Y") -> 10 | M11: =(EDATE(personel[[#This Row],[Date d''entrée]], 12)) -> 42723
A12: E0011 | B12: GROS | C12: Nicolas | D12: F | E12: 30318 | F12: 43822 | G12: Marseille | H12: Finance | I12: CDI | J12: 2721.95 | K12: =DATEDIF(personel[[#This Row],[Date de naissance]], TODAY(), "Y") -> 43 | L12: =DATEDIF(personel[[#This Row],[Date d''entrée]], TODAY(), "Y") -> 6 | M12: =(EDATE(personel[[#This Row],[Date d''entrée]], 12)) -> 44188
A13: E0012 | B13: JOUBERT | C13: Paulette | D13: F | E13: 38092 | F13: 42415 | G13: Lyon | H13: Finance | I13: CDI | J13: 2720.56 | K13: =DATEDIF(personel[[#This Row],[Date de naissance]], TODAY(), "Y") -> 22 | L13: =DATEDIF(personel[[#This Row],[Date d''entrée]], TODAY(), "Y") -> 10 | M13: =(EDATE(personel[[#This Row],[Date d''entrée]], 12)) -> 42781
... A251: E0250 | B251: LOPEZ | C251: Adèle | D251: H | E251: 36160 | F251: 42248 | G251: Marseille | H251: RH | I251: CDI | J251: 3242.99 | K251: =DATEDIF(personel[[#This Row],[Date de naissance]], TODAY(), "Y") -> 27 | L251: =DATEDIF(personel[[#This Row],[Date d''entrée]], TODAY(), "Y") -> 10 | M251: =(EDATE(personel[[#This Row],[Date d''entrée]], 12)) -> 42614

Sheet absences
A1: ID employé | B1: Service | C1: Mois | D1: Type d'absence | E1: Nombre de jours
A2: E0001 | B2: Production | C2: 45505 | D2: Congés payés | E2: 9
A3: E0002 | B3: Commercial | C3: 45566 | D3: Congés payés | E3: 3
A4: E0002 | B4: Commercial | C4: 45536 | D4: Congés payés | E4: 7
A5: E0002 | B5: Commercial | C5: 45536 | D5: Sans solde | E5: 1
A6: E0002 | B6: Commercial | C6: 45627 | D6: Congés payés | E6: 2
A7: E0003 | B7: Marketing | C7: 45413 | D7: Accident du travail | E7: 8
A8: E0004 | B8: Marketing | C8: 45323 | D8: Maladie | E8: 1
A9: E0008 | B9: Production | C9: 45352 | D9: Congés payés | E9: 3
A10: E0008 | B10: Production | C10: 45474 | D10: Congés payés | E10: 8
A11: E0008 | B11: Production | C11: 45413 | D11: Congés payés | E11: 5
A12: E0009 | B12: Finance | C12: 45505 | D12: Congés payés | E12: 2
A13: E0009 | B13: Finance | C13: 45444 | D13: Congés payés | E13: 8
... A357: E0250 | B357: RH | C357: 45292 | D357: Maladie | E357: 3

Sheet formations
A1: ID employé | B1: Service | C1: Intitulé de formation | D1: Durée (jours) | E1: Coût | F1: Date
A2: E0001 | B2: Production | C2: Techniques de vente | D2: 3 | E2: 1500 | F2: 45712 | H2: Service | I2: Nombre de formation
A3: E0003 | B3: Marketing | C3: Communication interpersonnelle | D3: 2 | E3: 606 | F3: 45798 | H3: Informatique | I3: =COUNTIF(B:B,H3) -> 17
A4: E0005 | B4: RH | C4: Management d'équipe | D4: 1 | E4: 397 | F4: 45732
A5: E0005 | B5: RH | C5: Techniques de vente | D5: 2 | E5: 1028 | F5: 45465
A6: E0006 | B6: Informatique | C6: RGPD et cybersécurité | D6: 1 | E6: 445 | F6: 45669
A7: E0008 | B7: Production | C7: Comptabilité analytique | D7: 3 | E7: 1020 | F7: 45505
A8: E0011 | B8: Finance | C8: Prise de parole en public | D8: 3 | E8: 1125 | F8: 45710
A9: E0015 | B9: Marketing | C9: Lean Management | D9: 3 | E9: 1299 | F9: 45560
A10: E0015 | B10: Marketing | C10: Prise de parole en public | D10: 2 | E10: 1036 | F10: 45517
A11: E0017 | B11: Finance | C11: Excel Avancé | D11: 1 | E11: 472 | F11: 45633
A12: E0018 | B12: Marketing | C12: Excel Avancé | D12: 2 | E12: 978 | F12: 45537
A13: E0022 | B13: Informatique | C13: RGPD et cybersécurité | D13: 1 | E13: 480 | F13: 45459
A14: E0023 | B14: RH | C14: RGPD et cybersécurité | D14: 2 | E14: 1162 | F14: 45472
A15: E0025 | B15: Informatique | C15: Techniques de vente | D15: 3 | E15: 930 | F15: 45760
... A136: E0247 | B136: Finance | C136: Analyse financière | D136: 2 | E136: 884 | F136: 45482

Sheet entretiens
A1: ID employé | B1: Service | C1: Date dernier entretien | D1: Évaluation | E1: Mois depuis entretien | F1: Alerte
A2: E0001 | B2: Production | C2: 45673 | D2: Très satisfaisant | E2: =DATEDIF(entretiens[[#This Row],[Date dernier entretien]], TODAY(), "M") -> 16 | F2: =IF(entretiens[[#This Row],[Mois depuis entretien]] > 12, "À contrôler", "") -> À contrôler
A3: E0002 | B3: Commercial | C3: 45391 | D3: Non réalisé | E3: =DATEDIF(entretiens[[#This Row],[Date dernier entretien]], TODAY(), "M") -> 25 | F3: =IF(entretiens[[#This Row],[Mois depuis entretien]] > 12, "À contrôler", "") -> À contrôler | H3: Evaluation | I3: Nombre
A4: E0003 | B4: Marketing | C4: 45533 | D4: Non réalisé | E4: =DATEDIF(entretiens[[#This Row],[Date dernier entretien]], TODAY(), "M") -> 20 | F4: =IF(entretiens[[#This Row],[Mois depuis entretien]] > 12, "À contrôler", "") -> À contrôler | H4: Non réalisé | I4: =COUNTIF(D:D,Tableau8[[#This Row],[Evaluation]]) -> 42
A5: E0004 | B5: Marketing | C5: 45266 | D5: À améliorer | E5: =DATEDIF(entretiens[[#This Row],[Date dernier entretien]], TODAY(), "M") -> 29 | F5: =IF(entretiens[[#This Row],[Mois depuis entretien]] > 12, "À contrôler", "") -> À contrôler | H5: À améliorer | I5: =COUNTIF(D:D,Tableau8[[#This Row],[Evaluation]]) -> 56
A6: E0005 | B6: RH | C6: 45442 | D6: À améliorer | E6: =DATEDIF(entretiens[[#This Row],[Date dernier entretien]], TODAY(), "M") -> 23 | F6: =IF(entretiens[[#This Row],[Mois depuis entretien]] > 12, "À contrôler", "") -> À contrôler | H6: Satisfaisant | I6: =COUNTIF(D:D,Tableau8[[#This Row],[Evaluation]]) -> 47
A7: E0006 | B7: Informatique | C7: 45177 | D7: Satisfaisant | E7: =DATEDIF(entretiens[[#This Row],[Date dernier entretien]], TODAY(), "M") -> 32 | F7: =IF(entretiens[[#This Row],[Mois depuis entretien]] > 12, "À contrôler", "") -> À contrôler | H7: Très satisfaisant | I7: =COUNTIF(D:D,Tableau8[[#This Row],[Evaluation]]) -> 60
A8: E0007 | B8: Informatique | C8: 45604 | D8: Non réalisé | E8: =DATEDIF(entretiens[[#This Row],[Date dernier entretien]], TODAY(), "M") -> 18 | F8: =IF(entretiens[[#This Row],[Mois depuis entretien]] > 12, "À contrôler", "") -> À contrôler | H8: Excellent | I8: =COUNTIF(D:D,Tableau8[[#This Row],[Evaluation]]) -> 45
A9: E0008 | B9: Production | C9: 45739 | D9: Très satisfaisant | E9: =DATEDIF(entretiens[[#This Row],[Date dernier entretien]], TODAY(), "M") -> 14 | F9: =IF(entretiens[[#This Row],[Mois depuis entretien]] > 12, "À contrôler", "") -> À contrôler
A10: E0009 | B10: Finance | C10: 45349 | D10: Satisfaisant | E10: =DATEDIF(entretiens[[#This Row],[Date dernier entretien]], TODAY(), "M") -> 26 | F10: =IF(entretiens[[#This Row],[Mois depuis entretien]] > 12, "À contrôler", "") -> À contrôler
A11: E0010 | B11: Marketing | C11: 45548 | D11: À améliorer | E11: =DATEDIF(entretiens[[#This Row],[Date dernier entretien]], TODAY(), "M") -> 20 | F11: =IF(entretiens[[#This Row],[Mois depuis entretien]] > 12, "À contrôler", "") -> À contrôler
A12: E0011 | B12: Finance | C12: 45739 | D12: À améliorer | E12: =DATEDIF(entretiens[[#This Row],[Date dernier entretien]], TODAY(), "M") -> 14 | F12: =IF(entretiens[[#This Row],[Mois depuis entretien]] > 12, "À contrôler", "") -> À contrôler
A13: E0012 | B13: Finance | C13: 45301 | D13: À améliorer | E13: =DATEDIF(entretiens[[#This Row],[Date dernier entretien]], TODAY(), "M") -> 28 | F13: =IF(entretiens[[#This Row],[Mois depuis entretien]] > 12, "À contrôler", "") -> À contrôler
A14: E0013 | B14: RH | C14: 45390 | D14: Non réalisé | E14: =DATEDIF(entretiens[[#This Row],[Date dernier entretien]], TODAY(), "M") -> 25 | F14: =IF(entretiens[[#This Row],[Mois depuis entretien]] > 12, "À contrôler", "") -> À contrôler
A15: E0014 | B15: RH | C15: 45523 | D15: Excellent | E15: =DATEDIF(entretiens[[#This Row],[Date dernier entretien]], TODAY(), "M") -> 21 | F15: =IF(entretiens[[#This Row],[Mois depuis entretien]] > 12, "À contrôler", "") -> À contrôler
A16: E0015 | B16: Marketing | C16: 45632 | D16: Non réalisé | E16: =DATEDIF(entretiens[[#This Row],[Date dernier entretien]], TODAY(), "M") -> 17 | F16: =IF(entretiens[[#This Row],[Mois depuis entretien]] > 12, "À contrôler", "") -> À contrôler
A17: E0016 | B17: Commercial | C17: 45568 | D17: Excellent | E17: =DATEDIF(entretiens[[#This Row],[Date dernier entretien]], TODAY(), "M") -> 19 | F17: =IF(entretiens[[#This Row],[Mois depuis entretien]] > 12, "À contrôler", "") -> À contrôler
A18: E0017 | B18: Finance | C18: 45694 | D18: Très satisfaisant | E18: =DATEDIF(entretiens[[#This Row],[Date dernier entretien]], TODAY(), "M") -> 15 | F18: =IF(entretiens[[#This Row],[Mois depuis entretien]] > 12, "À contrôler", "") -> À contrôler
A19: E0018 | B19: Marketing | C19: 45356 | D19: Excellent | E19: =DATEDIF(entretiens[[#This Row],[Date dernier entretien]], TODAY(), "M") -> 26 | F19: =IF(entretiens[[#This Row],[Mois depuis entretien]] > 12, "À contrôler", "") -> À contrôler
A20: E0019 | B20: Commercial | C20: 45466 | D20: À améliorer | E20: =DATEDIF(entretiens[[#This Row],[Date dernier entretien]], TODAY(), "M") -> 23 | F20: =IF(entretiens[[#This Row],[Mois depuis entretien]] > 12, "À contrôler", "") -> À contrôler
... A251: E0250 | B251: RH | C251: 45246 | D251: Satisfaisant | E251: =DATEDIF(entretiens[[#This Row],[Date dernier entretien]], TODAY(), "M") -> 30 | F251: =IF(entretiens[[#This Row],[Mois depuis entretien]] > 12, "À contrôler", "") -> À contrôler

Sheet turnover
A1: ID employé | B1: Service | C1: Date de départ | D1: Motif du départ
A2: E0143 | B2: Finance | C2: 45767 | D2: Démission
A3: E0007 | B3: Informatique | C3: 45576 | D3: Démission
A4: E0098 | B4: Informatique | C4: 45481 | D4: Démission
A5: E0061 | B5: Commercial | C5: 45570 | D5: Démission
A6: E0113 | B6: Informatique | C6: 45568 | D6: Démission
A7: E0182 | B7: RH | C7: 45687 | D7: Démission
A8: E0198 | B8: Commercial | C8: 45509 | D8: Démission
A9: E0185 | B9: RH | C9: 45625 | D9: Démission
A10: E0010 | B10: Marketing | C10: 45728 | D10: Démission
A11: E0105 | B11: Finance | C11: 45579 | D11: Démission
A12: E0201 | B12: Production | C12: 45507 | D12: Démission
A13: E0217 | B13: Commercial | C13: 45693 | D13: Démission
... A31: E0121 | B31: Finance | C31: 45540 | D31: Démission
A34: Taux de départ par service
A35: Service | B35: Départs | C35: Effectif | D35: Taux de départ
A36: Commercial | B36: =COUNTIF(quittances[Service],Taux_de_départ_par_service[[#This Row],[Service]]) -> 7 | C36: =COUNTIF(personel!H:H,Taux_de_départ_par_service[[#This Row],[Service]]) -> 40 | D36: =Taux_de_départ_par_service[[#This Row],[Départs]]/Taux_de_départ_par_service[[#This Row],[Effectif]] -> 0.175
A37: Finance | B37: =COUNTIF(quittances[Service],Taux_de_départ_par_service[[#This Row],[Service]]) -> 7 | C37: =COUNTIF(personel!H:H,Taux_de_départ_par_service[[#This Row],[Service]]) -> 36 | D37: =Taux_de_départ_par_service[[#This Row],[Départs]]/Taux_de_départ_par_service[[#This Row],[Effectif]] -> 0.19444444
A38: Informatique | B38: =COUNTIF(quittances[Service],Taux_de_départ_par_service[[#This Row],[Service]]) -> 4 | C38: =COUNTIF(personel!H:H,Taux_de_départ_par_service[[#This Row],[Service]]) -> 40 | D38: =Taux_de_départ_par_service[[#This Row],[Départs]]/Taux_de_départ_par_service[[#This Row],[Effectif]] -> 0.1
A39: Marketing | B39: =COUNTIF(quittances[Service],Taux_de_départ_par_service[[#This Row],[Service]]) -> 4 | C39: =COUNTIF(personel!H:H,Taux_de_départ_par_service[[#This Row],[Service]]) -> 46 | D39: =Taux_de_départ_par_service[[#This Row],[Départs]]/Taux_de_départ_par_service[[#This Row],[Effectif]] -> 0.086956522
A40: Production | B40: =COUNTIF(quittances[Service],Taux_de_départ_par_service[[#This Row],[Service]]) -> 4 | C40: =COUNTIF(personel!H:H,Taux_de_départ_par_service[[#This Row],[Service]]) -> 47 | D40: =Taux_de_départ_par_service[[#This Row],[Départs]]/Taux_de_départ_par_service[[#This Row],[Effectif]] -> 0.085106383
A41: RH | B41: =COUNTIF(quittances[Service],Taux_de_départ_par_service[[#This Row],[Service]]) -> 4 | C41: =COUNTIF(personel!H:H,Taux_de_départ_par_service[[#This Row],[Service]]) -> 41 | D41: =Taux_de_départ_par_service[[#This Row],[Départs]]/Taux_de_départ_par_service[[#This Row],[Effectif]] -> 0.097560976

Sheet Indicateurs RH
A1: Étiquettes de lignes | B1: Moyenne de Salaire brut mensuel | G1: Étiquettes de lignes | H1: Nombre de ID | M1: Étiquettes de lignes | N1: Moyenne de Salaire brut mensuel | Q1: Étiquettes de lignes | R1: Nombre de Sexe
A2: Lyon | B2: 2924.5171 | G2: Commercial | H2: 40 | M2: Commercial | N2: 2932.2585 | Q2: F | R2: 120
A3: Commercial | B3: 2848.01 | G3: F | H3: 20 | M3: Finance | N3: 2903.8031 | Q3: H | R3: 130
A4: Finance | B4: 2803.1676 | G4: H | H4: 20 | M4: Informatique | N4: 2919.5787 | Q4: Total général | R4: 250
A5: Informatique | B5: 3011.4529 | G5: Finance | H5: 36 | M5: Marketing | N5: 3066.2896
A6: Marketing | B6: 2960.002 | G6: F | H6: 18 | M6: Production | N6: 3135.9453
A7: Production | B7: 2862.0389 | G7: H | H7: 18 | M7: RH | N7: 2999.3756
A8: RH | B8: 3064.5191 | G8: Informatique | H8: 40 | M8: Total général | N8: 3000.0942
A9: Marseille | B9: 3000.0082 | G9: F | H9: 12
A10: Commercial | B10: 3031.8573 | G10: H | H10: 28
A11: Finance | B11: 3041.6122 | G11: Marketing | H11: 46
A12: Informatique | B12: 2968.9008 | G12: F | H12: 27
A13: Marketing | B13: 2992.6315 | G13: H | H13: 19
A14: Production | B14: 3135.2553 | G14: Production | H14: 47
A15: RH | B15: 2783.5909 | G15: F | H15: 24
A16: Paris | B16: 3067.5275 | G16: H | H16: 23
A17: Commercial | B17: 2891.7407 | G17: RH | H17: 41
A18: Finance | B18: 2950.855 | G18: F | H18: 19
A19: Informatique | B19: 2771.3154 | G19: H | H19: 22
A20: Marketing | B20: 3303.4669 | G20: Total général | H20: 250
A21: Production | B21: 3243.5761
A22: RH | B22: 3086.5889
A23: Total général | B23: 3000.0942

Sheet Synthèse_Absences
A1: 10 Salariés les plus absents
A2: ID employé | B2: Jours d'absence
A3: E0001 | B3: =SUMIF(absences!A:A,Top10_Absence_Salariés[[#This Row],[ID employé]],absences!E:E) -> 9
A4: E0002 | B4: =SUMIF(absences!A:A,Top10_Absence_Salariés[[#This Row],[ID employé]],absences!E:E) -> 13
A5: E0003 | B5: =SUMIF(absences!A:A,Top10_Absence_Salariés[[#This Row],[ID employé]],absences!E:E) -> 8
A6: E0004 | B6: =SUMIF(absences!A:A,Top10_Absence_Salariés[[#This Row],[ID employé]],absences!E:E) -> 1
A7: E0008 | B7: =SUMIF(absences!A:A,Top10_Absence_Salariés[[#This Row],[ID employé]],absences!E:E) -> 16
A8: E0009 | B8: =SUMIF(absences!A:A,Top10_Absence_Salariés[[#This Row],[ID employé]],absences!E:E) -> 10
A9: E0010 | B9: =SUMIF(absences!A:A,Top10_Absence_Salariés[[#This Row],[ID employé]],absences!E:E) -> 1
A10: E0011 | B10: =SUMIF(absences!A:A,Top10_Absence_Salariés[[#This Row],[ID employé]],absences!E:E) -> 3
A11: E0012 | B11: =SUMIF(absences!A:A,Top10_Absence_Salariés[[#This Row],[ID employé]],absences!E:E) -> 8
A12: E0013 | B12: =SUMIF(absences!A:A,Top10_Absence_Salariés[[#This Row],[ID employé]],absences!E:E) -> 5
A13: E0015 | B13: =SUMIF(absences!A:A,Top10_Absence_Salariés[[#This Row],[ID employé]],absences!E:E) -> 1
A14: E0078 | B14: =SUMIF(absences!A:A,Top10_Absence_Salariés[[#This Row],[ID employé]],absences!E:E) -> 34
... A184: E0250 | B184: =SUMIF(absences!A:A,Top10_Absence_Salariés[[#This Row],[ID employé]],absences!E:E) -> 3
A188: Taux d'absentéisme par service et par mois
A189: Service | B189: Mois | C189: Jours absence | D189: Taux Absentéisme
A190: Commercial | B190: 45292 | C190: =SUMIFS(absences!E:E, absences!B:B, Taux_absentéisme_service_mois[[#This Row],[Service]], absences!C:C, Taux_absentéisme_service_mois[[#This Row],[Mois]]) -> 28 | D190: =C190/(COUNTIF(personel!H:H,Synthèse_Absences!A190)*20) -> 0.035
A191: Commercial | B191: 45323 | C191: =SUMIFS(absences!E:E, absences!B:B, Taux_absentéisme_service_mois[[#This Row],[Service]], absences!C:C, Taux_absentéisme_service_mois[[#This Row],[Mois]]) -> 31 | D191: =C191/(COUNTIF(personel!H:H,Synthèse_Absences!A191)*20) -> 0.03875
A192: Commercial | B192: 45352 | C192: =SUMIFS(absences!E:E, absences!B:B, Taux_absentéisme_service_mois[[#This Row],[Service]], absences!C:C, Taux_absentéisme_service_mois[[#This Row],[Mois]]) -> 14 | D192: =C192/(COUNTIF(personel!H:H,Synthèse_Absences!A192)*20) -> 0.0175
A193: Commercial | B193: 45383 | C193: =SUMIFS(absences!E:E, absences!B:B, Taux_absentéisme_service_mois[[#This Row],[Service]], absences!C:C, Taux_absentéisme_service_mois[[#This Row],[Mois]]) -> 14 | D193: =C193/(COUNTIF(personel!H:H,Synthèse_Absences!A193)*20) -> 0.0175
A194: Commercial | B194: 45413 | C194: =SUMIFS(absences!E:E, absences!B:B, Taux_absentéisme_service_mois[[#This Row],[Service]], absences!C:C, Taux_absentéisme_service_mois[[#This Row],[Mois]]) -> 39 | D194: =C194/(COUNTIF(personel!H:H,Synthèse_Absences!A194)*20) -> 0.04875
A195: Commercial | B195: 45444 | C195: =SUMIFS(absences!E:E, absences!B:B, Taux_absentéisme_service_mois[[#This Row],[Service]], absences!C:C, Taux_absentéisme_service_mois[[#This Row],[Mois]]) -> 18 | D195: =C195/(COUNTIF(personel!H:H,Synthèse_Absences!A195)*20) -> 0.0225
A196: Commercial | B196: 45474 | C196: =SUMIFS(absences!E:E, absences!B:B, Taux_absentéisme_service_mois[[#This Row],[Service]], absences!C:C, Taux_absentéisme_service_mois[[#This Row],[Mois]]) -> 23 | D196: =C196/(COUNTIF(personel!H:H,Synthèse_Absences!A196)*20) -> 0.02875
A197: Commercial | B197: 45505 | C197: =SUMIFS(absences!E:E, absences!B:B, Taux_absentéisme_service_mois[[#This Row],[Service]], absences!C:C, Taux_absentéisme_service_mois[[#This Row],[Mois]]) -> 12 | D197: =C197/(COUNTIF(personel!H:H,Synthèse_Absences!A197)*20) -> 0.015
A198: Commercial | B198: 45536 | C198: =SUMIFS(absences!E:E, absences!B:B, Taux_absentéisme_service_mois[[#This Row],[Service]], absences!C:C, Taux_absentéisme_service_mois[[#This Row],[Mois]]) -> 45 | D198: =C198/(COUNTIF(personel!H:H,Synthèse_Absences!A198)*20) -> 0.05625
A199: Commercial | B199: 45566 | C199: =SUMIFS(absences!E:E, absences!B:B, Taux_absentéisme_service_mois[[#This Row],[Service]], absences!C:C, Taux_absentéisme_service_mois[[#This Row],[Mois]]) -> 57 | D199: =C199/(COUNTIF(personel!H:H,Synthèse_Absences!A199)*20) -> 0.07125
A200: Commercial | B200: 45597 | C200: =SUMIFS(absences!E:E, absences!B:B, Taux_absentéisme_service_mois[[#This Row],[Service]], absences!C:C, Taux_absentéisme_service_mois[[#This Row],[Mois]]) -> 30 | D200: =C200/(COUNTIF(personel!H:H,Synthèse_Absences!A200)*20) -> 0.0375
A201: Commercial | B201: 45627 | C201: =SUMIFS(absences!E:E, absences!B:B, Taux_absentéisme_service_mois[[#This Row],[Service]], absences!C:C, Taux_absentéisme_service_mois[[#This Row],[Mois]]) -> 2 | D201: =C201/(COUNTIF(personel!H:H,Synthèse_Absences!A201)*20) -> 0.0025
... A260: RH | B260: 45627 | C260: =SUMIFS(absences!E:E, absences!B:B, Taux_absentéisme_service_mois[[#This Row],[Service]], absences!C:C, Taux_absentéisme_service_mois[[#This Row],[Mois]]) -> 28 | D260: =C260/(COUNTIF(personel!H:H,Synthèse_Absences!A260)*20) -> 0.034146341

Sheet Tableau_de_bord
J7: Taux de départ par service
F8: =COUNTA(personel!A:A) -1 -> 250 | J8: Service | K8: Départs | L8: Effectif | M8: Taux de départ
J9: Commercial | K9: =COUNTIF(quittances[Service],Taux_de_départ_par_service12[[#This Row],[Service]]) -> 7 | L9: =COUNTIF(personel!Q:Q,Taux_de_départ_par_service12[[#This Row],[Service]]) -> 0 | M9: =turnover!B36/turnover!C36 -> 0.175
J10: Finance | K10: =COUNTIF(quittances[Service],Taux_de_départ_par_service12[[#This Row],[Service]]) -> 7 | L10: =COUNTIF(personel!Q:Q,Taux_de_départ_par_service12[[#This Row],[Service]]) -> 0 | M10: =turnover!B37/turnover!C37 -> 0.19444444
J11: Informatique | K11: =COUNTIF(quittances[Service],Taux_de_départ_par_service12[[#This Row],[Service]]) -> 4 | L11: =COUNTIF(personel!Q:Q,Taux_de_départ_par_service12[[#This Row],[Service]]) -> 0 | M11: =turnover!B38/turnover!C38 -> 0.1
J12: Marketing | K12: =COUNTIF(quittances[Service],Taux_de_départ_par_service12[[#This Row],[Service]]) -> 4 | L12: =COUNTIF(personel!Q:Q,Taux_de_départ_par_service12[[#This Row],[Service]]) -> 0 | M12: =turnover!B39/turnover!C39 -> 0.086956522
F13: =COUNTIFS(quittances[Date de départ], ">=" & DATE(YEAR(TODAY()), 1, 1), quittances[Date de départ], "<=" & DATE(YEAR(TODAY()), 12, 31)) -> 0 | J13: Production | K13: =COUNTIF(quittances[Service],Taux_de_départ_par_service12[[#This Row],[Service]]) -> 4 | L13: =COUNTIF(personel!Q:Q,Taux_de_départ_par_service12[[#This Row],[Service]]) -> 0 | M13: =turnover!B40/turnover!C40 -> 0.085106383
J14: RH | K14: =COUNTIF(quittances[Service],Taux_de_départ_par_service12[[#This Row],[Service]]) -> 4 | L14: =COUNTIF(personel!Q:Q,Taux_de_départ_par_service12[[#This Row],[Service]]) -> 0 | M14: =turnover!B41/turnover!C41 -> 0.097560976

Sheet TCD abs-mois
A3: Étiquettes de lignes | B3: Somme de Nombre de jours
A4: janv | B4: 136
A5: févr | B5: 129
A6: mars | B6: 93
A7: avr | B7: 92
A8: mai | B8: 183
A9: juin | B9: 94
A10: juil | B10: 126
A11: août | B11: 114
A12: sept | B12: 143
A13: oct | B13: 181
A14: nov | B14: 110
A15: déc | B15: 106
A16: Total général | B16: 1507
